hack4u/__init__.py
hack4u/courses.py
hack4u/utils.py
Academy_hack4u-0.5.0.dist-info/METADATA
Academy_hack4u-0.5.0.dist-info/WHEEL
Academy_hack4u-0.5.0.dist-info/top_level.txt
Academy_hack4u-0.5.0.dist-info/RECORD
